recipe2txt/__init__.py
recipe2txt/fetcher.py
recipe2txt/fetcher_async.py
recipe2txt/file_setup.py
recipe2txt/html2recipe.py
recipe2txt/parsing_error.py
recipe2txt/py.typed
recipe2txt/re2txt.py
recipe2txt/recipes2out.py
recipe2txt/sql.py
recipe2txt/user_interface.py
recipe2txt/utils/ArgConfig.py
recipe2txt/utils/ContextLogger.py
recipe2txt/utils/__init__.py
recipe2txt/utils/conditional_imports.py
recipe2txt/utils/filesystem.py
recipe2txt/utils/markdown.py
recipe2txt/utils/misc.py
recipe2txt/utils/traceback_utils.py
recipe2txt-0.5.3.dist-info/LICENSE
recipe2txt-0.5.3.dist-info/METADATA
recipe2txt-0.5.3.dist-info/WHEEL
recipe2txt-0.5.3.dist-info/entry_points.txt
recipe2txt-0.5.3.dist-info/top_level.txt
recipe2txt-0.5.3.dist-info/RECORD
