Metadata-Version: 2.2
Name: recipe2txt
Version: 0.5.3
Summary: Scrapes recipes and converts them to txt or markdown
Author-email: Jan Philipp Berg <git.7ksst@aleeas.com>
License: GNU General Public License v3 or later (GPLv3+)
Project-URL: Homepage, https://github.com/jp-berg/recipe2txt
Project-URL: Bug Tracker, https://github.com/jp-berg/recipe2txt/issues
Keywords: recipes,cooking,scraping,website
Classifier: Programming Language :: Python :: 3
Classifier: License :: OSI Approved :: MIT License
Classifier: Operating System :: POSIX :: Linux
Classifier: Development Status :: 3 - Alpha
Classifier: Environment :: Console
Classifier: Framework :: aiohttp
Classifier: Intended Audience :: End Users/Desktop
Classifier: License :: OSI Approved :: GNU General Public License v3 or later (GPLv3+)
Classifier: Operating System :: POSIX :: Linux
Classifier: Programming Language :: Python
Classifier: Topic :: Internet
Classifier: Topic :: Text Processing :: Markup :: Markdown
Classifier: Typing :: Typed
Requires-Python: >=3.10
License-File: LICENSE
Requires-Dist: aiodns~=3.2
Requires-Dist: aiohttp~=3.9
Requires-Dist: backports.strenum~=1.2; python_version < "3.11"
Requires-Dist: importlib-metadata~=8.5
Requires-Dist: jinja2~=3.1
Requires-Dist: lxml==5.0.2
Requires-Dist: recipe-scrapers~=15.3
Requires-Dist: tomli~=2.0; python_version < "3.11"
Requires-Dist: typing_extensions~=4.6.2; python_version < "3.11"
Requires-Dist: validators~=0.28
Requires-Dist: xdg-base-dirs~=6.0
